odoo/addons/l10n_be_cooperator_website_national_number/README.rst
odoo/addons/l10n_be_cooperator_website_national_number/__init__.py
odoo/addons/l10n_be_cooperator_website_national_number/__manifest__.py
odoo/addons/l10n_be_cooperator_website_national_number/controllers/__init__.py
odoo/addons/l10n_be_cooperator_website_national_number/controllers/main.py
odoo/addons/l10n_be_cooperator_website_national_number/i18n/it.po
odoo/addons/l10n_be_cooperator_website_national_number/i18n/l10n_be_cooperator_national_number.pot
odoo/addons/l10n_be_cooperator_website_national_number/i18n/l10n_be_cooperator_website_national_number.pot
odoo/addons/l10n_be_cooperator_website_national_number/readme/CONTRIBUTORS.rst
odoo/addons/l10n_be_cooperator_website_national_number/readme/DESCRIPTION.rst
odoo/addons/l10n_be_cooperator_website_national_number/readme/HISTORY.rst
odoo/addons/l10n_be_cooperator_website_national_number/readme/ROADMAP.rst
odoo/addons/l10n_be_cooperator_website_national_number/static/description/icon.png
odoo/addons/l10n_be_cooperator_website_national_number/static/description/index.html
odoo/addons/l10n_be_cooperator_website_national_number/views/subscription_template.xml
odoo_addon_l10n_be_cooperator_website_national_number-16.0.2.0.0.3.dist-info/METADATA
odoo_addon_l10n_be_cooperator_website_national_number-16.0.2.0.0.3.dist-info/WHEEL
odoo_addon_l10n_be_cooperator_website_national_number-16.0.2.0.0.3.dist-info/top_level.txt
odoo_addon_l10n_be_cooperator_website_national_number-16.0.2.0.0.3.dist-info/RECORD
